MANIFEST.in
README.rst
setup.cfg
setup.py
django_kuldeep.egg-info/PKG-INFO
django_kuldeep.egg-info/SOURCES.txt
django_kuldeep.egg-info/dependency_links.txt
django_kuldeep.egg-info/not-zip-safe
django_kuldeep.egg-info/requires.txt
django_kuldeep.egg-info/top_level.txt
kuldeep/__init__.py
kuldeep/admin.py
kuldeep/apps.py
kuldeep/models.py
kuldeep/serializers.py
kuldeep/tests.py
kuldeep/views.py
kuldeep/migrations/0001_initial.py
kuldeep/migrations/0002_bread.py
kuldeep/migrations/__init__.py