Metadata-Version: 2.1
Name: django-kuldeep
Version: 1.7
Summary: database package
Home-page: https://github.com/SoftprodigyIndia/django-kuldeep/invitations
Author: kuldeep khatana
Author-email: kuldeep.si.softprodigy@gmail.com
License: BSD-3-Clause  # Example license
Keywords: database-package
Platform: UNKNOWN
Classifier: Programming Language :: Python :: 3
Classifier: License :: OSI Approved :: MIT License
Classifier: Operating System :: OS Independent
Requires-Python: >=3.5
